nixstatsagent/__init__.py
nixstatsagent/nixstatsagent.py
nixstatsagent/plugins/__init__.py
nixstatsagent/plugins/cpu.py
nixstatsagent/plugins/diskusage.py
nixstatsagent/plugins/httpd.py
nixstatsagent/plugins/iostat.py
nixstatsagent/plugins/litespeed.py
nixstatsagent/plugins/loadavg.py
nixstatsagent/plugins/memory.py
nixstatsagent/plugins/mongodb.py
nixstatsagent/plugins/mysql.py
nixstatsagent/plugins/network.py
nixstatsagent/plugins/nginx.py
nixstatsagent/plugins/phpfpm.py
nixstatsagent/plugins/ping.py
nixstatsagent/plugins/plugins.py
nixstatsagent/plugins/process.py
nixstatsagent/plugins/sleeper.py
nixstatsagent/plugins/swap.py
nixstatsagent/plugins/system.py
nixstatsagent-1.1.29.data/data/share/doc/nixstatsagent/nixstats-example.ini
nixstatsagent-1.1.29.data/data/share/doc/nixstatsagent/LICENSE
nixstatsagent-1.1.29.data/data/share/doc/nixstatsagent/README.md
nixstatsagent-1.1.29.dist-info/top_level.txt
nixstatsagent-1.1.29.dist-info/entry_points.txt
nixstatsagent-1.1.29.dist-info/METADATA
nixstatsagent-1.1.29.dist-info/DESCRIPTION.rst
nixstatsagent-1.1.29.dist-info/metadata.json
nixstatsagent-1.1.29.dist-info/WHEEL
nixstatsagent-1.1.29.dist-info/RECORD
