Metadata-Version: 2.0
Name: nixstatsagent
Version: 1.1.29
Summary: NixStats agent
Home-page: https://github.com/NIXStats/nixstatsagent
Author: Al Nikolov
Author-email: root@toor.fi.eu.org
License: BSD-3-Clause
Keywords: nixstats system monitoring agent
Platform: UNKNOWN
Classifier: Development Status :: 5 - Production/Stable
Classifier: Environment :: No Input/Output (Daemon)
Classifier: Intended Audience :: System Administrators
Classifier: License :: OSI Approved :: BSD License
Classifier: Natural Language :: English
Classifier: Operating System :: POSIX :: Linux
Classifier: Programming Language :: Python :: 2.4
Classifier: Programming Language :: Python :: 2.5
Classifier: Programming Language :: Python :: 2.6
Classifier: Programming Language :: Python :: 2.7
Classifier: Topic :: System :: Monitoring
Requires-Dist: psutil
Requires-Dist: netifaces
